LICENSE
MANIFEST.in
README.rst
setup.py
infoblox/__init__.py
infoblox/cli.py
infoblox/exceptions.py
infoblox/mapping.py
infoblox/record.py
infoblox/session.py
infoblox.egg-info/PKG-INFO
infoblox.egg-info/SOURCES.txt
infoblox.egg-info/dependency_links.txt
infoblox.egg-info/entry_points.txt
infoblox.egg-info/requires.txt
infoblox.egg-info/top_level.txt
infoblox.egg-info/zip-safe