Metadata-Version: 1.1
Name: infoblox
Version: 1.1.1
Summary: Interface and CLI application for Infoblox NIOS
Home-page: https://github.com/gmr/infoblox
Author: Gavin M. Roy
Author-email: gavinmroy@gmail.com
License: Copyright (c) 2013 Gavin M. Roy
